check_s3_bucket/__init__.py
check_s3_bucket-0.2.6.dist-info/LICENSE.txt
check_s3_bucket-0.2.6.dist-info/METADATA
check_s3_bucket-0.2.6.dist-info/WHEEL
check_s3_bucket-0.2.6.dist-info/entry_points.txt
check_s3_bucket-0.2.6.dist-info/top_level.txt
check_s3_bucket-0.2.6.dist-info/RECORD
