Metadata-Version: 2.1
Name: check-s3-bucket
Version: 0.2.6
Summary: Check that a file was added to an S3 bucket in the given
Home-page: https://git.shore.co.il/nimrod/check_s3_bucket
Author: Nimrod Adar
Author-email: nimrod@shore.co.il
License: MIT
Keywords: nagios s3 aws monitoring
Platform: UNKNOWN
Classifier: Development Status :: 4 - Beta
Classifier: Intended Audience :: System Administrators
Classifier: Programming Language :: Python :: 3
Classifier: Programming Language :: Python :: 3.4
Classifier: Programming Language :: Python :: 3.5
Classifier: Programming Language :: Python :: 3.6
Classifier: Programming Language :: Python :: 3.7
Classifier: Programming Language :: Python :: 2
Classifier: Programming Language :: Python :: 2.7
Classifier: Topic :: Utilities
Classifier: License :: OSI Approved :: MIT License
Requires-Dist: pytz
Requires-Dist: botocore
